rxing-0.1.0.dist-info/METADATA
rxing-0.1.0.dist-info/WHEEL
rxing-0.1.0.dist-info/licenses/LICENSE
rxing/__init__.py
rxing/rxing_lib.cpython-313-x86_64-linux-gnu.so
rxing-0.1.0.dist-info/RECORD
