Metadata-Version: 2.4
Name: rxing
Version: 0.1.0
Classifier: Programming Language :: Rust
Classifier: Programming Language :: Python :: Implementation :: CPython
Classifier: Programming Language :: Python :: Implementation :: PyPy
Requires-Dist: pillow
Requires-Dist: numpy
License-File: LICENSE
Requires-Python: >=3.8
